bunnyhop/__init__.py
bunnyhop/base.py
bunnyhop/billing.py
bunnyhop/core.py
bunnyhop/purge.py
bunnyhop/stats.py
bunnyhop/storage.py
bunnyhop/url_settings.py
bunnyhop/zone.py
bunnyhop-0.1.1.dist-info/LICENSE
bunnyhop-0.1.1.dist-info/WHEEL
bunnyhop-0.1.1.dist-info/METADATA
bunnyhop-0.1.1.dist-info/RECORD
