Metadata-Version: 2.1
Name: bunnyhop
Version: 0.1.1
Summary: A Python library created make building with BunnyCDN easier
Home-page: https://github.com/capless/bunnyhop
License: Apache-2.0
Keywords: bunnycdn json db
Author: Brian Jinwright
Requires-Python: >=3.7,<4.0
Classifier: License :: OSI Approved :: Apache Software License
Classifier: Programming Language :: Python :: 3
Classifier: Programming Language :: Python :: 3.7
Classifier: Programming Language :: Python :: 3.8
Requires-Dist: envs (>=1.3,<2.0)
Requires-Dist: requests (>=2.23.0,<3.0.0)
Requires-Dist: valley (>=1.5.5,<2.0.0)
Project-URL: Repository, https://github.com/capless/bunnyhop
